<?xml version="1.0"?>
<RouteScheme xmlns:xsd="http://www.w3.org/2001/XMLSchema" xmlns:xsi="http://www.w3.org/2001/XMLSchema-instance" MaxBlockId="3">
  <Blocks>
    <BlockBase xsi:type="StartBlock">
      <Id>1</Id>
      <BlockTypeId xsi:nil="true" />
      <CustomProperties />
      <ParameterOperations />
    </BlockBase>
    <BlockBase xsi:type="FinishBlock">
      <Id>2</Id>
      <BlockTypeId xsi:nil="true" />
      <CustomProperties />
      <ParameterOperations />
      <UnderReview>false</UnderReview>
      <ReviewAssignmentId>0</ReviewAssignmentId>
    </BlockBase>
    <BlockBase xsi:type="AssignmentBlock">
      <Id>3</Id>
      <BlockTypeId xsi:nil="true" />
      <CreatedInTaskGuid>54262f8d-3f43-45a1-8825-13a229ba0283</CreatedInTaskGuid>
      <Title>Ознакомление с документом по поддержке</Title>
      <CustomProperties />
      <ParameterOperations />
      <GroupsAttachmentsRights />
      <AttachmentGroupsSettings />
      <TypeGuid>17229c8d-50e7-4f71-a570-4b2f5680a280</TypeGuid>
      <CreatedEntitiesIds />
      <Performers />
      <IsStopped>false</IsStopped>
      <IsParallel>false</IsParallel>
      <AbsoluteDeadline>0001-01-01T00:00:00</AbsoluteDeadline>
      <RelativeDeadline>1.00:00:00</RelativeDeadline>
      <RelativeDeadlineDays>1</RelativeDeadlineDays>
      <RelativeDeadlineHours>0</RelativeDeadlineHours>
      <RelativeDeadlineTimeBase xsi:nil="true" />
      <AbsoluteStopAssignmentsDeadline>0001-01-01T00:00:00</AbsoluteStopAssignmentsDeadline>
      <RelativeStopAssignmentsDeadline>00:00:00</RelativeStopAssignmentsDeadline>
      <RelativeStopDeadlineDays xsi:nil="true" />
      <RelativeStopDeadlineHours xsi:nil="true" />
      <AbsoluteStopAssignmentsDeadlineInternal>0001-01-01T00:00:00</AbsoluteStopAssignmentsDeadlineInternal>
      <ExecutionResults />
    </BlockBase>
  </Blocks>
  <Edges>
    <Edge>
      <Id>1</Id>
      <Source>1</Source>
      <Target>3</Target>
    </Edge>
    <Edge>
      <Id>2</Id>
      <Source>3</Source>
      <Target>2</Target>
    </Edge>
  </Edges>
  <Layout>
    <BlocksLayout>
      <BlockLayout>
        <BlockId>1</BlockId>
        <Bounds>
          <Location>
            <X>5</X>
            <Y>-15</Y>
          </Location>
          <Size>
            <Width>48</Width>
            <Height>48</Height>
          </Size>
          <X>5</X>
          <Y>-15</Y>
          <Width>48</Width>
          <Height>48</Height>
        </Bounds>
      </BlockLayout>
      <BlockLayout>
        <BlockId>2</BlockId>
        <Bounds>
          <Location>
            <X>5</X>
            <Y>223</Y>
          </Location>
          <Size>
            <Width>48</Width>
            <Height>48</Height>
          </Size>
          <X>5</X>
          <Y>223</Y>
          <Width>48</Width>
          <Height>48</Height>
        </Bounds>
      </BlockLayout>
      <BlockLayout>
        <BlockId>3</BlockId>
        <Bounds>
          <Location>
            <X>-96</X>
            <Y>93</Y>
          </Location>
          <Size>
            <Width>250</Width>
            <Height>70</Height>
          </Size>
          <X>-96</X>
          <Y>93</Y>
          <Width>250</Width>
          <Height>70</Height>
        </Bounds>
      </BlockLayout>
    </BlocksLayout>
    <EdgesLayout>
      <EdgeLayout>
        <DestinationAnchor>3</DestinationAnchor>
        <EdgeId>1</EdgeId>
        <EndPoint>
          <X>29</X>
          <Y>93</Y>
        </EndPoint>
        <OriginAnchor>3</OriginAnchor>
        <Points>
          <Point>
            <X>29</X>
            <Y>33</Y>
          </Point>
          <Point>
            <X>29</X>
            <Y>93</Y>
          </Point>
        </Points>
        <StartPoint>
          <X>29</X>
          <Y>33</Y>
        </StartPoint>
      </EdgeLayout>
      <EdgeLayout>
        <DestinationAnchor>1</DestinationAnchor>
        <EdgeId>2</EdgeId>
        <EndPoint>
          <X>29</X>
          <Y>223</Y>
        </EndPoint>
        <OriginAnchor>10</OriginAnchor>
        <Points>
          <Point>
            <X>29</X>
            <Y>163</Y>
          </Point>
          <Point>
            <X>29</X>
            <Y>223</Y>
          </Point>
          <Point>
            <X>29</X>
            <Y>223</Y>
          </Point>
        </Points>
        <StartPoint>
          <X>29</X>
          <Y>163</Y>
        </StartPoint>
      </EdgeLayout>
    </EdgesLayout>
  </Layout>
</RouteScheme>